zca/__init__.py
zca/version.py
zca/zca.py
zca-0.1.1.dist-info/LICENSE
zca-0.1.1.dist-info/METADATA
zca-0.1.1.dist-info/WHEEL
zca-0.1.1.dist-info/top_level.txt
zca-0.1.1.dist-info/RECORD
