Metadata-Version: 2.1
Name: zca
Version: 0.1.1
Summary: ZCA whitening
Home-page: https://github.com/davebulaval/zca
Author: Maarten Versteegh, David Beauchemin
Author-email: maartenversteegh@gmail.com
Classifier: Development Status :: 5 - Production/Stable
Classifier: Programming Language :: Python
Classifier: Programming Language :: Python :: 3
Classifier: Programming Language :: Python :: 3.7
Classifier: Programming Language :: Python :: 3.8
Classifier: Programming Language :: Python :: 3.9
Classifier: Programming Language :: Python :: 3.10
License-File: LICENSE
Requires-Dist: numpy
Requires-Dist: scipy
Requires-Dist: scikit-learn
